poetry_ci_updater/__init__.py
poetry_ci_updater/main.py
poetry_ci_updater/providers/__init__.py
poetry_ci_updater/providers/gitlab.py
poetry_ci_updater/providers/provider.py
poetry_ci_updater-0.1.0.dist-info/entry_points.txt
poetry_ci_updater-0.1.0.dist-info/LICENSE
poetry_ci_updater-0.1.0.dist-info/WHEEL
poetry_ci_updater-0.1.0.dist-info/METADATA
poetry_ci_updater-0.1.0.dist-info/RECORD
