Metadata-Version: 2.1
Name: poetry-ci-updater
Version: 0.1.0
Summary: 
Home-page: https://github.com/MarcoGlauser/poetry-ci-updater
License: MIT
Keywords: poetry,ci,auto updater
Author: MarcoGlauser
Requires-Python: >=3.6,<4.0
Classifier: License :: OSI Approved :: MIT License
Classifier: Programming Language :: Python :: 3
Classifier: Programming Language :: Python :: 3.6
Classifier: Programming Language :: Python :: 3.7
Classifier: Programming Language :: Python :: 3.8
Requires-Dist: click (>=7.0,<8.0)
Requires-Dist: gitpython (>=3.0.0,<4.0.0)
Requires-Dist: requests (>=2.22.0,<3.0.0)
Project-URL: Repository, https://github.com/MarcoGlauser/poetry-ci-updater
